slack_notifications/__init__.py
slack_notifications/slack_messages.py
slack_notifications_datateam-0.0.9.dist-info/LICENSE
slack_notifications_datateam-0.0.9.dist-info/METADATA
slack_notifications_datateam-0.0.9.dist-info/WHEEL
slack_notifications_datateam-0.0.9.dist-info/top_level.txt
slack_notifications_datateam-0.0.9.dist-info/RECORD
