Metadata-Version: 2.1
Name: slack-notifications-datateam
Version: 0.0.9
Summary: Small package to send slack notifications
Home-page: https://github.com/ClipMX/pypi.slack-notifications-datateam
Author: Lizbeth Mancilla
Author-email: lizbeth.mancilla@payclip.com
License: UNKNOWN
Platform: UNKNOWN
Classifier: Programming Language :: Python :: 3
Classifier: License :: OSI Approved :: MIT License
Classifier: Operating System :: OS Independent
Requires-Python: >=3.6
